factoryfloor_helpers/__init__.py
factoryfloor_helpers/context_services/__init__.py
factoryfloor_helpers/context_services/holiday.py
factoryfloor_helpers/context_services/table.py
factoryfloor_helpers/environment/__init__.py
factoryfloor_helpers/environment/urls.py
f9_factoryfloor_helpers-0.1.1.dev1.dist-info/METADATA
f9_factoryfloor_helpers-0.1.1.dev1.dist-info/WHEEL
f9_factoryfloor_helpers-0.1.1.dev1.dist-info/top_level.txt
f9_factoryfloor_helpers-0.1.1.dev1.dist-info/RECORD
