Metadata-Version: 2.4
Name: f9-factoryfloor-helpers
Version: 0.1.1.dev1
Summary: Helper tools for FactoryFloor projects
Home-page: https://github.com/factoryfloor/factoryfloor-helpers
Author: FactoryFloor Team
Author-email: team@factoryfloor.example.com
Classifier: Programming Language :: Python :: 3
Classifier: License :: OSI Approved :: MIT License
Classifier: Operating System :: OS Independent
Requires-Python: >=3.7
Requires-Dist: pydantic
Requires-Dist: nagerapi
Requires-Dist: five9-python>=0.0.4.dev3
Requires-Dist: datetime
Dynamic: author
Dynamic: author-email
Dynamic: classifier
Dynamic: description
Dynamic: description-content-type
Dynamic: home-page
Dynamic: requires-dist
Dynamic: requires-python
Dynamic: summary
